iron_sdk/__init__.py
iron_sdk/config.py
iron_sdk/context.py
iron_sdk/decorators.py
iron_sdk/errors.py
iron_sdk/integrations/__init__.py
iron_sdk/integrations/autogpt.py
iron_sdk/integrations/crewai.py
iron_sdk/integrations/langchain.py
iron_sdk-0.2.0.dist-info/licenses/license
iron_sdk-0.2.0.dist-info/METADATA
iron_sdk-0.2.0.dist-info/WHEEL
iron_sdk-0.2.0.dist-info/top_level.txt
iron_sdk-0.2.0.dist-info/RECORD
