Metadata-Version: 2.4
Name: iron-sdk
Version: 0.2.0
Summary: Pythonic SDK layer for Iron Cage agent protection with decorators and framework integrations
Author: Iron Cage Team
License: Apache-2.0
Classifier: Development Status :: 3 - Alpha
Classifier: Intended Audience :: Developers
Classifier: License :: OSI Approved :: Apache Software License
Classifier: Programming Language :: Python :: 3
Classifier: Programming Language :: Python :: 3.9
Classifier: Programming Language :: Python :: 3.10
Classifier: Programming Language :: Python :: 3.11
Classifier: Programming Language :: Python :: 3.12
Requires-Python: >=3.9
License-File: license
Requires-Dist: iron-runtime>=0.2.0
Provides-Extra: dev
Requires-Dist: pytest>=8.0.0; extra == "dev"
Requires-Dist: pytest-cov>=4.0.0; extra == "dev"
Requires-Dist: black>=24.0.0; extra == "dev"
Requires-Dist: mypy>=1.0.0; extra == "dev"
Requires-Dist: ruff>=0.1.0; extra == "dev"
Provides-Extra: langchain
Requires-Dist: langchain>=0.1.0; extra == "langchain"
Provides-Extra: crewai
Requires-Dist: crewai>=0.1.0; extra == "crewai"
Provides-Extra: autogpt
Requires-Dist: autogpt>=0.1.0; extra == "autogpt"
Provides-Extra: all
Requires-Dist: langchain>=0.1.0; extra == "all"
Requires-Dist: crewai>=0.1.0; extra == "all"
Requires-Dist: autogpt>=0.1.0; extra == "all"
Dynamic: license-file
